smoosense/__init__.py
smoosense/app.py
smoosense/exceptions.py
smoosense/my_logging.py
smoosense/widget.py
smoosense/cli/__init__.py
smoosense/cli/server.py
smoosense/cli/state.py
smoosense/cli/utils.py
smoosense/emb/__init__.py
smoosense/emb/models.py
smoosense/emb/path_grouping.py
smoosense/emb/sense_images.py
smoosense/emb/sense_videos.py
smoosense/handlers/__init__.py
smoosense/handlers/auth.py
smoosense/handlers/fs.py
smoosense/handlers/lance.py
smoosense/handlers/pages.py
smoosense/handlers/parquet.py
smoosense/handlers/query.py
smoosense/handlers/s3.py
smoosense/handlers/umap.py
smoosense/lance/__init__.py
smoosense/lance/db_client.py
smoosense/lance/models.py
smoosense/lance/parquet_to_lance.py
smoosense/lance/table_client.py
smoosense/statics/404.html
smoosense/statics/DB.html
smoosense/statics/DB.txt
smoosense/statics/FolderBrowser.html
smoosense/statics/FolderBrowser.txt
smoosense/statics/LiteTable.html
smoosense/statics/LiteTable.txt
smoosense/statics/MiniTable.html
smoosense/statics/MiniTable.txt
smoosense/statics/Table.html
smoosense/statics/Table.txt
smoosense/statics/favicon.ico
smoosense/statics/index.html
smoosense/statics/index.txt
smoosense/statics/_next/static/azP_P7NKpY6mKl5e02I7-/_buildManifest.js
smoosense/statics/_next/static/azP_P7NKpY6mKl5e02I7-/_ssgManifest.js
smoosense/statics/_next/static/chunks/06d028f4-d7f236a86cd66aa4.js
smoosense/statics/_next/static/chunks/1417.66369e8fdbf37d13.js
smoosense/statics/_next/static/chunks/1768.4c42efd3e769c6e4.js
smoosense/statics/_next/static/chunks/191d07e0-df4a879656760d37.js
smoosense/statics/_next/static/chunks/2354-4f716cad57dd64f6.js
smoosense/statics/_next/static/chunks/2418-4fee9e798de7e467.js
smoosense/statics/_next/static/chunks/2577-327d318a5527999a.js
smoosense/statics/_next/static/chunks/2599-2996ed05f1cb6544.js
smoosense/statics/_next/static/chunks/3019-aeb6bc46b336504c.js
smoosense/statics/_next/static/chunks/340.5077053f48d14a5b.js
smoosense-0.1.35.dist-info/licenses/LICENSE
smoosense-0.1.35.dist-info/METADATA
smoosense-0.1.35.dist-info/WHEEL
smoosense-0.1.35.dist-info/entry_points.txt
smoosense-0.1.35.dist-info/top_level.txt
smoosense-0.1.35.dist-info/RECORD
