Metadata-Version: 2.4
Name: smoosense
Version: 0.1.35
Summary: Smoothly make sense of your large multi-modal datasets
Author-email: SmooSense AI <contact@smoosense.ai>
License: Apache-2.0
Project-URL: Homepage, https://smoosense.ai
Project-URL: Documentation, https://smoosense.ai/docs/
Project-URL: Repository, https://github.com/SmooSenseAI/smoosense
Project-URL: Source Code, https://github.com/SmooSenseAI/smoosense
Project-URL: Bug Tracker, https://github.com/SmooSenseAI/smoosense/issues
Project-URL: Changelog, https://github.com/SmooSenseAI/smoosense/releases
Keywords: data-analysis,visualization,multimodal,parquet,csv,sql,duckdb
Classifier: Development Status :: 4 - Beta
Classifier: Intended Audience :: Developers
Classifier: Intended Audience :: Science/Research
Classifier: License :: OSI Approved :: Apache Software License
Classifier: Programming Language :: Python :: 3
Classifier: Programming Language :: Python :: 3.9
Classifier: Programming Language :: Python :: 3.10
Classifier: Programming Language :: Python :: 3.11
Classifier: Programming Language :: Python :: 3.12
Classifier: Topic :: Scientific/Engineering :: Visualization
Classifier: Topic :: Database
Classifier: Topic :: Software Development :: Libraries :: Python Modules
Requires-Python: >=3.9
License-File: LICENSE
Requires-Dist: authlib>=1.0
Requires-Dist: boto3>=1.39.11
Requires-Dist: click>=8.1.8
Requires-Dist: duckdb>=1.2.1
Requires-Dist: flask>=3.1.0
Requires-Dist: lancedb>=0.25.2
Requires-Dist: pyarrow>=20.0.0
Requires-Dist: pydantic>=2.11.7
Requires-Dist: pytz>=2025.2
Requires-Dist: requests>=2.32.3
Requires-Dist: rich>=14.0.0
Provides-Extra: jupyter
Requires-Dist: pandas>=2.3.0; extra == "jupyter"
Requires-Dist: pyarrow>=20.0.0; extra == "jupyter"
Requires-Dist: ipython>=8.0.0; extra == "jupyter"
Provides-Extra: daft
Requires-Dist: smoosense[jupyter]; extra == "daft"
Requires-Dist: daft>=0.3.0; extra == "daft"
Provides-Extra: emb
Requires-Dist: torch>=2.0.0; extra == "emb"
Requires-Dist: pillow>=10.0.0; extra == "emb"
Requires-Dist: hdbscan>=0.8.40; extra == "emb"
Requires-Dist: opencv-python-headless>=4.8.0; extra == "emb"
Requires-Dist: tqdm>=4.67.1; extra == "emb"
Requires-Dist: transformers>=4.57.3; extra == "emb"
Requires-Dist: umap-learn>=0.5.9.post2; extra == "emb"
Dynamic: license-file
